nuvolos_cli/__init__.py
nuvolos_cli/__main__.py
nuvolos_cli/api_client.py
nuvolos_cli/config.py
nuvolos_cli/interface.py
nuvolos_cli/logging.py
nuvolos_cli/utils.py
nuvolos_cli/version.py
nuvolos_cli-1.1.1.dist-info/licenses/LICENSE
nuvolos_cli-1.1.1.dist-info/METADATA
nuvolos_cli-1.1.1.dist-info/WHEEL
nuvolos_cli-1.1.1.dist-info/entry_points.txt
nuvolos_cli-1.1.1.dist-info/top_level.txt
nuvolos_cli-1.1.1.dist-info/RECORD
