Metadata-Version: 2.4
Name: nuvolos-cli
Version: 1.1.1
Summary: Command-line interface for Nuvolos
Author-email: Alphacruncher <support@nuvolos.cloud>
License-Expression: MIT
Project-URL: Repository, https://github.com/nuvolos-cloud/nuvolos-cli
Project-URL: Documentation, https://nuvolos-cli.readthedocs.io/en/latest
Classifier: Development Status :: 5 - Production/Stable
Classifier: Intended Audience :: Science/Research
Classifier: Operating System :: OS Independent
Classifier: Programming Language :: Python
Classifier: Programming Language :: Python :: 3 :: Only
Classifier: Programming Language :: Python :: 3.8
Classifier: Programming Language :: Python :: 3.9
Classifier: Programming Language :: Python :: 3.10
Classifier: Programming Language :: Python :: 3.11
Classifier: Programming Language :: Python :: 3.12
Classifier: Topic :: Scientific/Engineering :: Bio-Informatics
Classifier: Topic :: Scientific/Engineering :: Artificial Intelligence
Requires-Python: >=3.8
License-File: LICENSE
Requires-Dist: click>=8.1.7
Requires-Dist: click-log>=0.4.0
Requires-Dist: tabulate>=0.9.0
Requires-Dist: pyyaml>=6.0.1
Requires-Dist: nuvolos-client-api==1.2.1
Requires-Dist: humanize>=4.9.0
Requires-Dist: python-slugify>=8.0.4
Dynamic: license-file
